odddML/__init__.py
odddML/custom_layers.py
odddML/setup.py
odddML/templateModels.py
odddML/utils.py
odddML/resnet/resnetModels.py
odddML/resnet/resnet_layers.py
odddML-0.1.1a0.dist-info/METADATA
odddML-0.1.1a0.dist-info/WHEEL
odddML-0.1.1a0.dist-info/top_level.txt
odddML-0.1.1a0.dist-info/RECORD
